pixverse_mcp/__init__.py
pixverse_mcp/__main__.py
pixverse_mcp/config.py
pixverse_mcp/exceptions.py
pixverse_mcp/server.py
pixverse_mcp/sse_server.py
pixverse_mcp/client/__init__.py
pixverse_mcp/client/base.py
pixverse_mcp/client/pixverse.py
pixverse_mcp/models/__init__.py
pixverse_mcp/models/common.py
pixverse_mcp/models/requests.py
pixverse_mcp/models/responses.py
pixverse_mcp/utils/__init__.py
pixverse_mcp/utils/helpers.py
pixverse_mcp/utils/validation.py
pixverse_mcp-0.2.2.dist-info/METADATA
pixverse_mcp-0.2.2.dist-info/WHEEL
pixverse_mcp-0.2.2.dist-info/entry_points.txt
pixverse_mcp-0.2.2.dist-info/RECORD
