Metadata-Version: 2.4
Name: pixverse-mcp
Version: 0.2.2
Summary: Model Context Protocol server for Pixverse video generation APIs
Project-URL: Homepage, https://github.com/pixverse/pixverse-mcp
Project-URL: Repository, https://github.com/pixverse/pixverse-mcp
Project-URL: Documentation, https://pixverse-mcp.readthedocs.io
Project-URL: Issues, https://github.com/pixverse/pixverse-mcp/issues
Author-email: Pixverse Team <dev@pixverse.ai>
License: MIT
Classifier: Development Status :: 4 - Beta
Classifier: Intended Audience :: Developers
Classifier: License :: OSI Approved :: MIT License
Classifier: Programming Language :: Python :: 3
Classifier: Programming Language :: Python :: 3.12
Requires-Python: >=3.12
Requires-Dist: asyncio-throttle>=1.0.0
Requires-Dist: fastapi>=0.104.0
Requires-Dist: httpx>=0.24.0
Requires-Dist: loguru>=0.7.0
Requires-Dist: mcp[cli]>=1.6.0
Requires-Dist: pydantic>=2.0.0
Requires-Dist: python-dotenv>=1.0.0
Requires-Dist: pyyaml>=6.0.0
Requires-Dist: sse-starlette>=1.6.0
Requires-Dist: tenacity>=8.0.0
Requires-Dist: uvicorn>=0.24.0
Provides-Extra: dev
Requires-Dist: black>=23.0.0; extra == 'dev'
Requires-Dist: flake8>=6.0.0; extra == 'dev'
Requires-Dist: isort>=5.12.0; extra == 'dev'
Requires-Dist: mypy>=1.0.0; extra == 'dev'
Requires-Dist: pre-commit>=3.0.0; extra == 'dev'
Requires-Dist: pytest-asyncio>=0.21.0; extra == 'dev'
Requires-Dist: pytest-cov>=4.0.0; extra == 'dev'
Requires-Dist: pytest>=7.0.0; extra == 'dev'
